__init__.py
ecallisto_ng/__init__.py
ecallisto_ng/burst_list/__init__.py
ecallisto_ng/burst_list/utils.py
ecallisto_ng/burst_list/data/burst_list.xlsx
ecallisto_ng/combine_antennas/__init__.py
ecallisto_ng/combine_antennas/combine.py
ecallisto_ng/combine_antennas/utils.py
ecallisto_ng/combine_antennas/virtualantenna.py
ecallisto_ng/data_download/__init__.py
ecallisto_ng/data_download/downloader.py
ecallisto_ng/data_download/hu_dataset.py
ecallisto_ng/data_download/utils.py
ecallisto_ng/data_fetching/__init__.py
ecallisto_ng/data_fetching/get_data.py
ecallisto_ng/data_fetching/get_information.py
ecallisto_ng/data_processing/__init__.py
ecallisto_ng/data_processing/utils.py
ecallisto_ng/plotting/__init__.py
ecallisto_ng/plotting/plotting.py
ecallisto_ng/plotting/utils.py
ecallisto_ng-1.1.7.dist-info/LICENSE
ecallisto_ng-1.1.7.dist-info/METADATA
ecallisto_ng-1.1.7.dist-info/WHEEL
ecallisto_ng-1.1.7.dist-info/top_level.txt
ecallisto_ng-1.1.7.dist-info/RECORD
