Metadata-Version: 2.1
Name: ecallisto-ng
Version: 1.1.7
Summary: A Python package for the fetching (and some processing and plotting) of eCallisto data based on request and pandas.
Author-email: Vincenzo Timmel <vincenzo.timmel@fhnw.ch>
Project-URL: Homepage, https://github.com/i4Ds/ecallisto_ng
Project-URL: Bug Tracker, https://github.com/i4Ds/ecallisto_ng/issues
Classifier: Programming Language :: Python :: 3
Classifier: License :: OSI Approved :: MIT License
Classifier: Operating System :: OS Independent
Requires-Python: <3.12,>=3.9
License-File: LICENSE
Requires-Dist: numpy<2.0.0
Requires-Dist: pandas>=2.0.0
Requires-Dist: openpyxl
Requires-Dist: plotly
Requires-Dist: kaleido
Requires-Dist: matplotlib
Requires-Dist: requests
Requires-Dist: scikit-image>=0.20.0
Requires-Dist: pyarrow
Requires-Dist: bs4
Requires-Dist: lxml
Requires-Dist: astropy
Requires-Dist: tqdm
Provides-Extra: nb
Requires-Dist: nbformat; extra == "nb"
Requires-Dist: ipython; extra == "nb"
Requires-Dist: ipykernel; extra == "nb"
Provides-Extra: dev
Requires-Dist: black; extra == "dev"
Requires-Dist: isort; extra == "dev"
Requires-Dist: twine; extra == "dev"
Requires-Dist: build; extra == "dev"
Requires-Dist: pytest; extra == "dev"
Provides-Extra: va
Requires-Dist: torch; extra == "va"
Provides-Extra: all
Requires-Dist: nbformat; extra == "all"
Requires-Dist: ipython; extra == "all"
Requires-Dist: ipykernel; extra == "all"
Requires-Dist: black; extra == "all"
Requires-Dist: isort; extra == "all"
Requires-Dist: twine; extra == "all"
Requires-Dist: build; extra == "all"
Requires-Dist: pytest; extra == "all"
Requires-Dist: torch; extra == "all"
